opentrain/__init__.py
opentrain/main.py
opentrain/config/__init__.py
opentrain/config/loader.py
opentrain/data/__init__.py
opentrain/data/factory.py
opentrain/engine/__init__.py
opentrain/engine/trainer.py
opentrain/models/__init__.py
opentrain/models/factory.py
opentrain_ml-0.0.1.dist-info/licenses/LICENSE
opentrain_ml-0.0.1.dist-info/METADATA
opentrain_ml-0.0.1.dist-info/WHEEL
opentrain_ml-0.0.1.dist-info/entry_points.txt
opentrain_ml-0.0.1.dist-info/top_level.txt
opentrain_ml-0.0.1.dist-info/RECORD
