Metadata-Version: 2.4
Name: opentrain-ml
Version: 0.0.1
Summary: Modular and extensible ML training framework
Author: Shramadeep
Author-email: shramadeep8@gmail.com
Classifier: Programming Language :: Python :: 3
Classifier: License :: OSI Approved :: MIT License
Classifier: Operating System :: OS Independent
Requires-Python: >=3.8
License-File: LICENSE
Requires-Dist: torch>=1.12
Requires-Dist: torchvision
Requires-Dist: PyYAML
Requires-Dist: tqdm
Requires-Dist: omegaconf
Requires-Dist: scikit-learn
Requires-Dist: wandb
Requires-Dist: rich
Dynamic: author
Dynamic: author-email
Dynamic: classifier
Dynamic: license-file
Dynamic: requires-dist
Dynamic: requires-python
Dynamic: summary
